lmapp/__init__.py
lmapp/auto_update.py
lmapp/cli.py
lmapp/cli_plugins.py
lmapp/installer.py
lmapp/backend/__init__.py
lmapp/backend/base.py
lmapp/backend/detector.py
lmapp/backend/installer.py
lmapp/backend/llamafile.py
lmapp/backend/ollama.py
lmapp/backend/uaft_integration.py
lmapp/batch/batch_processor.py
lmapp/commands/plugin_cli.py
lmapp/core/__init__.py
lmapp/core/async_llm.py
lmapp/core/auth.py
lmapp/core/batch.py
lmapp/core/cache.py
lmapp/core/chat.py
lmapp/core/cli_terminal.py
lmapp/core/config.py
lmapp/core/error_db.py
lmapp/core/feature_gate.py
lmapp/core/multi_llm.py
lmapp/core/nux.py
lmapp/core/optimization.py
lmapp/core/plugins.py
lmapp/core/rag.py
lmapp/core/sessions.py
lmapp/core/shell_customizer.py
lmapp/core/sync_manager.py
lmapp/core/system_prompts.py
lmapp/core/trial.py
lmapp/core/workflow.py
lmapp/plugins/__init__.py
lmapp/plugins/base.py
lmapp/plugins/editor.py
lmapp/plugins/example_cache_manager.py
lmapp/plugins/example_code_analyzer.py
lmapp/plugins/example_code_refactoring.py
lmapp/plugins/example_dependency_auditor.py
lmapp/plugins/example_document_chatbot.py
lmapp/plugins/example_git_flow.py
lmapp/plugins/example_knowledge_base.py
lmapp/plugins/example_qa_bot.py
lmapp/plugins/example_summarizer.py
lmapp/plugins/example_translator.py
lmapp/plugins/manager.py
lmapp/plugins/plugin_manager.py
lmapp/plugins/plugin_marketplace.py
lmapp/plugins/registry.py
lmapp/plugins/terminal.py
lmapp/rag/async_search.py
lmapp/rag/cache.py
lmapp/rag/chroma_store.py
lmapp/rag/citation_tracker.py
lmapp/rag/document_processor.py
lmapp/rag/embedding.py
lmapp/rag/hybrid_search.py
lmapp/rag/ingestion.py
lmapp/rag/models.py
lmapp/rag/rag_system.py
lmapp/rag/vector_store.py
lmapp/rag/vector_store_impl.py
lmapp/server/analysis_service.py
lmapp/server/app.py
lmapp/server/refactoring_service.py
lmapp/server/streaming.py
lmapp/server/workflow_routes.py
lmapp/ui/__init__.py
lmapp/ui/chat_ui.py
lmapp/ui/first_run.py
lmapp/ui/menu.py
lmapp/ui/menu_old.py
lmapp/ui/prompt.py
lmapp-0.4.1.dist-info/licenses/LICENSE
lmapp-0.4.1.dist-info/METADATA
lmapp-0.4.1.dist-info/WHEEL
lmapp-0.4.1.dist-info/entry_points.txt
lmapp-0.4.1.dist-info/top_level.txt
lmapp-0.4.1.dist-info/RECORD
