Metadata-Version: 2.4
Name: lmapp
Version: 0.4.1
Summary: Local LLM Made Simple - Consumer-friendly AI assistant
Author-email: lmapp Contributors <dev@lmapp.dev>
License: MIT
Project-URL: Homepage, https://github.com/nabaznyl/lmapp
Project-URL: Documentation, https://github.com/nabaznyl/lmapp
Project-URL: Source, https://github.com/nabaznyl/lmapp
Project-URL: Tracker, https://github.com/nabaznyl/lmapp/issues
Project-URL: Releases, https://github.com/nabaznyl/lmapp/releases
Project-URL: PyPI, https://pypi.org/project/lmapp
Keywords: ai,llm,local,offline,cli,terminal,privacy
Requires-Python: >=3.8
License-File: LICENSE
Requires-Dist: requests>=2.31.0
Requires-Dist: click>=8.1.0
Requires-Dist: rich>=13.7.0
Requires-Dist: pydantic>=2.0.0
Requires-Dist: inquirer>=3.1.0
Requires-Dist: psutil>=5.9.0
Requires-Dist: distro>=1.8.0
Requires-Dist: loguru>=0.7.2
Requires-Dist: fastapi>=0.109.0
Requires-Dist: uvicorn>=0.27.0
Requires-Dist: aiofiles>=23.2.1
Requires-Dist: PyYAML>=6.0.0
Provides-Extra: dev
Requires-Dist: pytest>=7.4.0; extra == "dev"
Requires-Dist: pytest-cov>=4.1.0; extra == "dev"
Requires-Dist: black>=23.12.0; extra == "dev"
Requires-Dist: flake8>=7.0.0; extra == "dev"
Requires-Dist: mypy>=1.8.0; extra == "dev"
Requires-Dist: uaft>=0.2.0; extra == "dev"
Provides-Extra: api
Dynamic: license-file
